pretty_midi/TimGM6mb.sf2
pretty_midi/__init__.py
pretty_midi/constants.py
pretty_midi/containers.py
pretty_midi/fluidsynth.py
pretty_midi/instrument.py
pretty_midi/pretty_midi.py
pretty_midi/utilities.py
pretty_midi_bfm-0.2.10.post1.dist-info/LICENSE.txt
pretty_midi_bfm-0.2.10.post1.dist-info/METADATA
pretty_midi_bfm-0.2.10.post1.dist-info/WHEEL
pretty_midi_bfm-0.2.10.post1.dist-info/top_level.txt
pretty_midi_bfm-0.2.10.post1.dist-info/RECORD
