Metadata-Version: 2.1
Name: pretty-midi-bfm
Version: 0.2.10.post1
Summary: PrettyMIDI with Bots for Music patches
Home-page: https://github.com/craffel/pretty-midi
Author: Colin Raffel (original author), Lars Monstad (fork maintainer)
Author-email: craffel@gmail.com
License: MIT
Project-URL: Homepage, https://github.com/craffel/pretty-midi
Keywords: audio,music,midi,mir
Classifier: License :: OSI Approved :: MIT License
Classifier: Programming Language :: Python
Classifier: Development Status :: 3 - Alpha
Classifier: Intended Audience :: Developers
Classifier: Topic :: Multimedia :: Sound/Audio :: MIDI
Requires-Python: >=3.9
License-File: LICENSE.txt
Requires-Dist: numpy >=1.7.0
Requires-Dist: mido >=1.1.16
Requires-Dist: six
Requires-Dist: importlib-resources
Provides-Extra: fluidsynth
Requires-Dist: pyfluidsynth >=1.3.1 ; extra == 'fluidsynth'
